jupyterlab_bxplorer/__init__.py
jupyterlab_bxplorer/_version.py
jupyterlab_bxplorer/config_handler.py
jupyterlab_bxplorer/download_history.py
jupyterlab_bxplorer/download_history_handler.py
jupyterlab_bxplorer/favorites.py
jupyterlab_bxplorer/favorites_handler.py
jupyterlab_bxplorer/file_manager_handler.py
jupyterlab_bxplorer/handlers.py
jupyterlab_bxplorer/labextension/build_log.json
jupyterlab_bxplorer/labextension/package.json
jupyterlab_bxplorer/labextension/schemas/jupyterlab-bxplorer/package.json.orig
jupyterlab_bxplorer/labextension/schemas/jupyterlab-bxplorer/plugin.json
jupyterlab_bxplorer/labextension/static/1e673ba8589654794d2a.woff2
jupyterlab_bxplorer/labextension/static/35dca8a7145a17c8d130.woff2
jupyterlab_bxplorer/labextension/static/8265f64786397d6b832d.woff2
jupyterlab_bxplorer/labextension/static/c948f1263341699b3c1e.woff2
jupyterlab_bxplorer/labextension/static/lib_index_js.1c5b36f3e417f93585d2.js
jupyterlab_bxplorer/labextension/static/lib_index_js.1c5b36f3e417f93585d2.js.map
jupyterlab_bxplorer/labextension/static/node_modules_emotion_use-insertion-effect-with-fallbacks_dist_emotion-use-insertion-effect-wi-3c9bb40.02f24ce7556a9514ff71.js
jupyterlab_bxplorer/labextension/static/node_modules_emotion_use-insertion-effect-with-fallbacks_dist_emotion-use-insertion-effect-wi-3c9bb40.02f24ce7556a9514ff71.js.map
jupyterlab_bxplorer/labextension/static/node_modules_emotion_use-insertion-effect-with-fallbacks_dist_emotion-use-insertion-effect-wi-3c9bb41.7c333b27d792dd7544fd.js
jupyterlab_bxplorer/labextension/static/node_modules_emotion_use-insertion-effect-with-fallbacks_dist_emotion-use-insertion-effect-wi-3c9bb41.7c333b27d792dd7544fd.js.map
jupyterlab_bxplorer/labextension/static/remoteEntry.6874ae4da29f72fad20d.js
jupyterlab_bxplorer/labextension/static/remoteEntry.6874ae4da29f72fad20d.js.map
jupyterlab_bxplorer/labextension/static/style.js
jupyterlab_bxplorer-0.2.30.dist-info/METADATA
jupyterlab_bxplorer-0.2.30.dist-info/WHEEL
jupyterlab_bxplorer-0.2.30.dist-info/licenses/LICENSE
jupyterlab_bxplorer-0.2.30.dist-info/RECORD
